{
    "output_file": "/scratch/40840274/tmpecfjsie6",
    "model": "C",
    "likelihood": -63.17711,
    "criteria": 7e-05,
    "params_mle": {
        "eps": 4.49969e-06,
        "eps_cont": 0,
        "lambda": 0,
        "theta_bar": 0.0007512932,
        "a": -1,
        "S_d": -12.77494,
        "b": 0.1864518,
        "p_b": 0.0009291351,
        "S_b": 0.007920274,
        "r": [
            0.7182839,
            0.8011416,
            0.8404934,
            0.7203041,
            0.7525535,
            0.7101008,
            0.7568956,
            0.945595
        ]
    },
    "n": 10,
    "expec": [
        {
            "E[P_z(1)]": 0.0007512902,
            "E[P_z(2)]": 0.00026982,
            "E[P_z(3)]": 0.0002006302,
            "E[P_z(4)]": 0.000157864,
            "E[P_z(5)]": 0.0001082319,
            "E[P_z(6)]": 9.42317e-05,
            "E[P_z(7)]": 7.6214e-05,
            "E[P_z(8)]": 7.10822e-05,
            "E[P_z(9)]": 7.89385e-05,
            "E[D_z]": null,
            "E[mis_z]": null
        },
        {
            "E[P_z(1)]": 0.0005683054,
            "E[P_z(2)]": 0.0001800133,
            "E[P_z(3)]": 0.00012451,
            "E[P_z(4)]": 9.32728e-05,
            "E[P_z(5)]": 6.16348e-05,
            "E[P_z(6)]": 5.21083e-05,
            "E[P_z(7)]": 4.11276e-05,
            "E[P_z(8)]": 3.75642e-05,
            "E[P_z(9)]": 4.09597e-05,
            "E[D_z]": null,
            "E[mis_z]": null
        }
    ],
    "alpha": 0.0028472397198279218,
    "execution_time": 57.10777282714844
}