{
    "py/object": "fastdfe.polydfe.PolyDFE",
    "logger": {
        "py/reduce": [
            {
                "py/function": "logging.getLogger"
            },
            {
                "py/tuple": [
                    "fastdfe.PolyDFE"
                ]
            }
        ]
    },
    "bootstraps": null,
    "config": {
        "py/object": "fastdfe.config.Config",
        "data": {
            "model": "GammaExpParametrization",
            "intervals_del": {
                "py/tuple": [
                    -100000000.0,
                    -1e-05,
                    1000
                ]
            },
            "intervals_ben": {
                "py/tuple": [
                    1e-05,
                    10000.0,
                    1000
                ]
            },
            "integration_mode": "midpoint",
            "linearized": true,
            "seed": 0,
            "opts_mle": {},
            "n_runs": 10,
            "x0": {
                "all": {
                    "S_b": 0.007920217,
                    "S_d": -15.49506,
                    "a": -1,
                    "b": 0.1773756,
                    "eps": 4.49946e-06,
                    "eps_cont": 0,
                    "lambda": 0,
                    "p_b": 0.0009289272,
                    "r": [
                        0.756295,
                        0.8118638,
                        0.8203224,
                        0.7703739,
                        0.7596918,
                        0.7652355,
                        0.8437457,
                        1.011566
                    ],
                    "theta_bar": 0.000731729
                }
            },
            "bounds": {},
            "scales": {},
            "fixed_params": {},
            "shared_params": [],
            "covariates": [],
            "sfs_neut": {
                "py/object": "fastdfe.spectrum.Spectra",
                "data": {
                    "all": [
                        879651.205708058,
                        652.0,
                        226.0,
                        178.0,
                        135.0,
                        103.0,
                        77.0,
                        81.0,
                        63.0,
                        54.0,
                        0.0
                    ]
                }
            },
            "sfs_sel": {
                "py/object": "fastdfe.spectrum.Spectra",
                "data": {
                    "all": [
                        2376150.79429194,
                        1308.0,
                        475.0,
                        229.0,
                        210.0,
                        156.0,
                        120.0,
                        76.0,
                        87.0,
                        95.0,
                        0.0
                    ]
                }
            },
            "do_bootstrap": false,
            "n_bootstraps": 10,
            "parallelize": false,
            "loss_type": "likelihood"
        }
    },
    "output_file": null,
    "execution_time": 41.55001950263977,
    "summary": {
        "py/object": "fastdfe.polydfe.PolyDFEResult",
        "output_file": "results/polydfe/hgdp/inference/1/opts.n.10.config.default/bootstraps/63/all.polydfe.txt",
        "postprocessing_source": "../resources/polydfe/postprocessing/script.R",
        "data": {
            "output_file": "/scratch/40840285/tmp9g7tb236",
            "model": "C",
            "likelihood": -71.67658,
            "criteria": 7e-05,
            "params_mle": {
                "eps": 4.50072e-06,
                "eps_cont": 0,
                "lambda": 0,
                "theta_bar": 0.0007312984,
                "a": -1,
                "S_d": -10.43068,
                "b": 0.2309365,
                "p_b": 0.000928836,
                "S_b": 0.007920235,
                "r": [
                    0.7841606,
                    0.720365,
                    0.8440089,
                    0.8134368,
                    0.7582657,
                    0.7173141,
                    0.794804,
                    0.8995459
                ]
            },
            "n": 10,
            "expec": [
                {
                    "E[P_z(1)]": 0.0007312955,
                    "E[P_z(2)]": 0.0002867267,
                    "E[P_z(3)]": 0.0001756001,
                    "E[P_z(4)]": 0.0001543053,
                    "E[P_z(5)]": 0.000118973,
                    "E[P_z(6)]": 9.242e-05,
                    "E[P_z(7)]": 7.49391e-05,
                    "E[P_z(8)]": 7.26558e-05,
                    "E[P_z(9)]": 7.30959e-05,
                    "E[D_z]": null,
                    "E[mis_z]": null
                },
                {
                    "E[P_z(1)]": 0.000553009,
                    "E[P_z(2)]": 0.0001884623,
                    "E[P_z(3)]": 0.0001060391,
                    "E[P_z(4)]": 8.78652e-05,
                    "E[P_z(5)]": 6.48015e-05,
                    "E[P_z(6)]": 4.85777e-05,
                    "E[P_z(7)]": 3.82372e-05,
                    "E[P_z(8)]": 3.61402e-05,
                    "E[P_z(9)]": 3.55577e-05,
                    "E[D_z]": null,
                    "E[mis_z]": null
                }
            ],
            "alpha": 0.003054026492987486,
            "execution_time": 41.55001950263977
        }
    }
}