{
    "output_file": "/scratch/38995562/tmp45gajj1z",
    "model": "C",
    "likelihood": -139.2621,
    "criteria": 6e-05,
    "params_mle": {
        "eps": 0,
        "eps_cont": 0,
        "lambda": 0,
        "theta_bar": 0.0008973669,
        "a": -1,
        "S_d": -404.3613,
        "b": 0.3344885,
        "p_b": 0,
        "S_b": 1,
        "r": [
            1.10587,
            1.111199,
            1.206971,
            1.329966,
            0.9444517,
            1.129334,
            0.8794154,
            1.098281,
            0.9471662,
            0.9450779,
            0.9420714,
            1.43566,
            1.100879,
            1.185609,
            0.9300565,
            1.132323,
            1.278119,
            1.322754
        ]
    },
    "n": 20,
    "expec": [
        {
            "E[P_z(1)]": 0.0008973669,
            "E[P_z(2)]": 0.0004961856,
            "E[P_z(3)]": 0.0003323844,
            "E[P_z(4)]": 0.0002707739,
            "E[P_z(5)]": 0.0002386936,
            "E[P_z(6)]": 0.0001412533,
            "E[P_z(7)]": 0.0001447753,
            "E[P_z(8)]": 9.86448e-05,
            "E[P_z(9)]": 0.0001095068,
            "E[P_z(10)]": 8.49956e-05,
            "E[P_z(11)]": 7.70983e-05,
            "E[P_z(12)]": 7.04486e-05,
            "E[P_z(13)]": 9.91011e-05,
            "E[P_z(14)]": 7.05637e-05,
            "E[P_z(15)]": 7.09284e-05,
            "E[P_z(16)]": 5.21626e-05,
            "E[P_z(17)]": 5.97711e-05,
            "E[P_z(18)]": 6.3719e-05,
            "E[P_z(19)]": 6.24734e-05,
            "E[D_z]": null,
            "E[mis_z]": null
        },
        {
            "E[P_z(1)]": 0.0002985481,
            "E[P_z(2)]": 0.0001179389,
            "E[P_z(3)]": 6.72046e-05,
            "E[P_z(4)]": 4.94084e-05,
            "E[P_z(5)]": 4.04357e-05,
            "E[P_z(6)]": 2.25819e-05,
            "E[P_z(7)]": 2.20746e-05,
            "E[P_z(8)]": 1.44514e-05,
            "E[P_z(9)]": 1.54976e-05,
            "E[P_z(10)]": 1.16682e-05,
            "E[P_z(11)]": 1.03003e-05,
            "E[P_z(12)]": 9.1836e-06,
            "E[P_z(13)]": 1.26326e-05,
            "E[P_z(14)]": 8.8116e-06,
            "E[P_z(15)]": 8.69e-06,
            "E[P_z(16)]": 6.2785e-06,
            "E[P_z(17)]": 7.0759e-06,
            "E[P_z(18)]": 7.4265e-06,
            "E[P_z(19)]": 7.175e-06,
            "E[D_z]": null,
            "E[mis_z]": null
        }
    ],
    "alpha": 0.0,
    "execution_time": 115.47909569740295
}