{
    "output_file": "/scratch/40840236/tmp18ls92kd",
    "model": "C",
    "likelihood": -33.27721,
    "criteria": 7e-05,
    "params_mle": {
        "eps": 4.49517e-06,
        "eps_cont": 0,
        "lambda": 0,
        "theta_bar": 0.0005573979,
        "a": -1,
        "S_d": -8.472967,
        "b": 0.2684123,
        "p_b": 0.01427099,
        "S_b": 0.1260169,
        "r": [
            0.9950405,
            0.9672409,
            0.9980373
        ]
    },
    "n": 5,
    "expec": [
        {
            "E[P_z(1)]": 0.000557396,
            "E[P_z(2)]": 0.0002773163,
            "E[P_z(3)]": 0.0001797131,
            "E[P_z(4)]": 0.0001390778,
            "E[D_z]": null,
            "E[mis_z]": null
        },
        {
            "E[P_z(1)]": 0.0003913267,
            "E[P_z(2)]": 0.0001648117,
            "E[P_z(3)]": 9.69491e-05,
            "E[P_z(4)]": 7.0244e-05,
            "E[D_z]": null,
            "E[mis_z]": null
        }
    ],
    "alpha": 0.03395398200188688,
    "execution_time": 24.459613800048828
}