{
    "output_file": "/scratch/38995756/tmp9x6cc9ph",
    "model": "C",
    "likelihood": -156.2711,
    "criteria": 8e-05,
    "params_mle": {
        "eps": 0,
        "eps_cont": 0,
        "lambda": 0,
        "theta_bar": 0.0009034314,
        "a": -1,
        "S_d": -213.0698,
        "b": 0.3881965,
        "p_b": 0,
        "S_b": 1,
        "r": [
            1.095172,
            1.066254,
            1.206089,
            1.149,
            0.8684197,
            1.116145,
            0.8318513,
            1.066421,
            1.016003,
            0.8129755,
            0.8747157,
            1.279456,
            1.159385,
            0.9187061,
            0.9195044,
            1.248277,
            1.357569,
            1.106964
        ]
    },
    "n": 20,
    "expec": [
        {
            "E[P_z(1)]": 0.0009034314,
            "E[P_z(2)]": 0.0004947065,
            "E[P_z(3)]": 0.0003210958,
            "E[P_z(4)]": 0.0002724047,
            "E[P_z(5)]": 0.0002076085,
            "E[P_z(6)]": 0.0001307596,
            "E[P_z(7)]": 0.0001440515,
            "E[P_z(8)]": 9.39401e-05,
            "E[P_z(9)]": 0.0001070487,
            "E[P_z(10)]": 9.17889e-05,
            "E[P_z(11)]": 6.67698e-05,
            "E[P_z(12)]": 6.58538e-05,
            "E[P_z(13)]": 8.89154e-05,
            "E[P_z(14)]": 7.48161e-05,
            "E[P_z(15)]": 5.53325e-05,
            "E[P_z(16)]": 5.19193e-05,
            "E[P_z(17)]": 6.63372e-05,
            "E[P_z(18)]": 6.81372e-05,
            "E[P_z(19)]": 5.26351e-05,
            "E[D_z]": null,
            "E[mis_z]": null
        },
        {
            "E[P_z(1)]": 0.0003325261,
            "E[P_z(2)]": 0.0001260978,
            "E[P_z(3)]": 6.79682e-05,
            "E[P_z(4)]": 5.11986e-05,
            "E[P_z(5)]": 3.5797e-05,
            "E[P_z(6)]": 2.10805e-05,
            "E[P_z(7)]": 2.19824e-05,
            "E[P_z(8)]": 1.36862e-05,
            "E[P_z(9)]": 1.49839e-05,
            "E[P_z(10)]": 1.24032e-05,
            "E[P_z(11)]": 8.7431e-06,
            "E[P_z(12)]": 8.3818e-06,
            "E[P_z(13)]": 1.10278e-05,
            "E[P_z(14)]": 9.061e-06,
            "E[P_z(15)]": 6.5555e-06,
            "E[P_z(16)]": 6.0265e-06,
            "E[P_z(17)]": 7.5539e-06,
            "E[P_z(18)]": 7.6206e-06,
            "E[P_z(19)]": 5.7878e-06,
            "E[D_z]": null,
            "E[mis_z]": null
        }
    ],
    "alpha": 0.0,
    "execution_time": 94.10636281967163
}