{
    "py/object": "fastdfe.polydfe.PolyDFE",
    "logger": {
        "py/reduce": [
            {
                "py/function": "logging.getLogger"
            },
            {
                "py/tuple": [
                    "fastdfe.PolyDFE"
                ]
            }
        ]
    },
    "bootstraps": null,
    "config": {
        "py/object": "fastdfe.config.Config",
        "data": {
            "model": "GammaExpParametrization",
            "intervals_del": {
                "py/tuple": [
                    -100000000.0,
                    -1e-05,
                    1000
                ]
            },
            "intervals_ben": {
                "py/tuple": [
                    1e-05,
                    10000.0,
                    1000
                ]
            },
            "integration_mode": "midpoint",
            "linearized": true,
            "seed": 0,
            "opts_mle": {},
            "n_runs": 10,
            "x0": {
                "all": {
                    "S_b": 0.05627203,
                    "S_d": -26.88451,
                    "a": -1,
                    "b": 0.1464485,
                    "eps": 4.50288e-06,
                    "eps_cont": 0,
                    "lambda": 0,
                    "p_b": 0.004419742,
                    "r": [
                        0.4932568,
                        0.4490162,
                        0.411058,
                        0.4293708,
                        0.4059378,
                        0.3950674,
                        0.4836194,
                        0.4412304,
                        0.4459431,
                        0.5171633,
                        0.4880109,
                        0.499798,
                        0.5114526,
                        0.4705895,
                        0.3840001,
                        0.3914661,
                        0.4942643,
                        0.4410675,
                        0.4295933,
                        0.3836019,
                        0.3386893,
                        0.4566943,
                        0.4425798,
                        0.4623484,
                        0.424307,
                        0.4116725,
                        0.4906384,
                        0.4335386,
                        0.4045893,
                        0.5819833,
                        0.4816641,
                        0.5724359,
                        0.5396078,
                        0.5300813,
                        0.62822,
                        0.8578236,
                        0.810246,
                        2.052769
                    ],
                    "theta_bar": 0.001050261
                }
            },
            "bounds": {},
            "scales": {},
            "fixed_params": {},
            "shared_params": [],
            "covariates": [],
            "sfs_neut": {
                "py/object": "fastdfe.spectrum.Spectra",
                "data": {
                    "all": [
                        1037949.33330917,
                        1078.0,
                        280.0,
                        152.0,
                        114.0,
                        74.0,
                        84.0,
                        43.0,
                        71.0,
                        49.0,
                        46.0,
                        57.0,
                        42.0,
                        40.0,
                        61.0,
                        37.0,
                        26.0,
                        26.0,
                        34.0,
                        26.0,
                        30.0,
                        17.0,
                        10.0,
                        21.0,
                        19.0,
                        18.0,
                        17.0,
                        16.0,
                        17.0,
                        9.0,
                        18.0,
                        18.0,
                        14.0,
                        16.0,
                        28.0,
                        11.0,
                        32.0,
                        17.0,
                        24.0,
                        64.0,
                        0.0
                    ]
                }
            },
            "sfs_sel": {
                "py/object": "fastdfe.spectrum.Spectra",
                "data": {
                    "all": [
                        2843477.66669083,
                        2533.0,
                        518.0,
                        309.0,
                        205.0,
                        162.0,
                        123.0,
                        136.0,
                        127.0,
                        96.0,
                        102.0,
                        62.0,
                        66.0,
                        66.0,
                        51.0,
                        66.0,
                        35.0,
                        36.0,
                        47.0,
                        31.0,
                        36.0,
                        37.0,
                        31.0,
                        37.0,
                        21.0,
                        20.0,
                        24.0,
                        17.0,
                        24.0,
                        26.0,
                        18.0,
                        38.0,
                        16.0,
                        32.0,
                        25.0,
                        21.0,
                        13.0,
                        36.0,
                        38.0,
                        95.0,
                        0.0
                    ]
                }
            },
            "do_bootstrap": false,
            "n_bootstraps": 10,
            "parallelize": false,
            "loss_type": "likelihood"
        }
    },
    "output_file": null,
    "execution_time": 904.548505783081,
    "summary": {
        "py/object": "fastdfe.polydfe.PolyDFEResult",
        "output_file": "results/polydfe/hgdp/inference/1/opts.n.40.config.default/bootstraps/78/all.polydfe.txt",
        "postprocessing_source": "../resources/polydfe/postprocessing/script.R",
        "data": {
            "output_file": "/scratch/40841858/tmps60fmg_y",
            "model": "C",
            "likelihood": -259.206,
            "criteria": 0.00061,
            "params_mle": {
                "eps": 4.50356e-06,
                "eps_cont": 0,
                "lambda": 0,
                "theta_bar": 0.001047239,
                "a": -1,
                "S_d": -17.81378,
                "b": 0.1740669,
                "p_b": 0.004414868,
                "S_b": 0.05625234,
                "r": [
                    0.4717983,
                    0.4260663,
                    0.4048315,
                    0.3828246,
                    0.4101932,
                    0.4200035,
                    0.5376906,
                    0.4478441,
                    0.5128179,
                    0.4574842,
                    0.4564686,
                    0.4887925,
                    0.5598082,
                    0.5549107,
                    0.3524876,
                    0.3826376,
                    0.5318874,
                    0.3968897,
                    0.4858403,
                    0.4190683,
                    0.334637,
                    0.4967218,
                    0.3587377,
                    0.3561881,
                    0.4009639,
                    0.3361675,
                    0.4344301,
                    0.3851852,
                    0.4109784,
                    0.6623381,
                    0.3672164,
                    0.6074076,
                    0.6926027,
                    0.4315112,
                    0.6255697,
                    0.7589262,
                    0.9136608,
                    2.409723
                ]
            },
            "n": 40,
            "expec": [
                {
                    "E[P_z(1)]": 0.001047235,
                    "E[P_z(2)]": 0.0002470418,
                    "E[P_z(3)]": 0.0001487305,
                    "E[P_z(4)]": 0.0001059885,
                    "E[P_z(5)]": 8.01815e-05,
                    "E[P_z(6)]": 7.15948e-05,
                    "E[P_z(7)]": 6.28347e-05,
                    "E[P_z(8)]": 7.03861e-05,
                    "E[P_z(9)]": 5.2111e-05,
                    "E[P_z(10)]": 5.37041e-05,
                    "E[P_z(11)]": 4.3554e-05,
                    "E[P_z(12)]": 3.98359e-05,
                    "E[P_z(13)]": 3.93755e-05,
                    "E[P_z(14)]": 4.18751e-05,
                    "E[P_z(15)]": 3.87415e-05,
                    "E[P_z(16)]": 2.30711e-05,
                    "E[P_z(17)]": 2.35714e-05,
                    "E[P_z(18)]": 3.09451e-05,
                    "E[P_z(19)]": 2.18757e-05,
                    "E[P_z(20)]": 2.54395e-05,
                    "E[P_z(21)]": 2.08983e-05,
                    "E[P_z(22)]": 1.59294e-05,
                    "E[P_z(23)]": 2.26168e-05,
                    "E[P_z(24)]": 1.56535e-05,
                    "E[P_z(25)]": 1.49207e-05,
                    "E[P_z(26)]": 1.61503e-05,
                    "E[P_z(27)]": 1.30389e-05,
                    "E[P_z(28)]": 1.62484e-05,
                    "E[P_z(29)]": 1.39098e-05,
                    "E[P_z(30)]": 1.43466e-05,
                    "E[P_z(31)]": 2.23752e-05,
                    "E[P_z(32)]": 1.20179e-05,
                    "E[P_z(33)]": 1.9276e-05,
                    "E[P_z(34)]": 2.13332e-05,
                    "E[P_z(35)]": 1.29116e-05,
                    "E[P_z(36)]": 1.81982e-05,
                    "E[P_z(37)]": 2.1481e-05,
                    "E[P_z(38)]": 2.51805e-05,
                    "E[P_z(39)]": 6.4711e-05,
                    "E[D_z]": null,
                    "E[mis_z]": null
                },
                {
                    "E[P_z(1)]": 0.0008849783,
                    "E[P_z(2)]": 0.0001898819,
                    "E[P_z(3)]": 0.0001074749,
                    "E[P_z(4)]": 7.32562e-05,
                    "E[P_z(5)]": 5.35488e-05,
                    "E[P_z(6)]": 4.65048e-05,
                    "E[P_z(7)]": 3.98776e-05,
                    "E[P_z(8)]": 4.37894e-05,
                    "E[P_z(9)]": 3.18607e-05,
                    "E[P_z(10)]": 3.23318e-05,
                    "E[P_z(11)]": 2.58601e-05,
                    "E[P_z(12)]": 2.3357e-05,
                    "E[P_z(13)]": 2.28231e-05,
                    "E[P_z(14)]": 2.40162e-05,
                    "E[P_z(15)]": 2.2002e-05,
                    "E[P_z(16)]": 1.29832e-05,
                    "E[P_z(17)]": 1.31516e-05,
                    "E[P_z(18)]": 1.71274e-05,
                    "E[P_z(19)]": 1.20161e-05,
                    "E[P_z(20)]": 1.38736e-05,
                    "E[P_z(21)]": 1.13196e-05,
                    "E[P_z(22)]": 8.5723e-06,
                    "E[P_z(23)]": 1.2096e-05,
                    "E[P_z(24)]": 8.3225e-06,
                    "E[P_z(25)]": 7.888e-06,
                    "E[P_z(26)]": 8.4917e-06,
                    "E[P_z(27)]": 6.82e-06,
                    "E[P_z(28)]": 8.456e-06,
                    "E[P_z(29)]": 7.2039e-06,
                    "E[P_z(30)]": 7.3954e-06,
                    "E[P_z(31)]": 1.14818e-05,
                    "E[P_z(32)]": 6.14e-06,
                    "E[P_z(33)]": 9.8064e-06,
                    "E[P_z(34)]": 1.08083e-05,
                    "E[P_z(35)]": 6.5154e-06,
                    "E[P_z(36)]": 9.1475e-06,
                    "E[P_z(37)]": 1.07569e-05,
                    "E[P_z(38)]": 1.25633e-05,
                    "E[P_z(39)]": 3.21715e-05,
                    "E[D_z]": null,
                    "E[mis_z]": null
                }
            ],
            "alpha": 0.010208970688071988,
            "execution_time": 904.548505783081
        }
    }
}