{
    "output_file": "/scratch/40841172/tmp_z99nebo",
    "model": "C",
    "likelihood": -142.1846,
    "criteria": 0.00158,
    "params_mle": {
        "eps": 4.49609e-06,
        "eps_cont": 0,
        "lambda": 0,
        "theta_bar": 0.0008776749,
        "a": -1,
        "S_d": -251.7228,
        "b": 0.0922184,
        "p_b": 0.003907824,
        "S_b": 0.03802471,
        "r": [
            0.5656242,
            0.5523606,
            0.5564964,
            0.4630205,
            0.5144045,
            0.6108616,
            0.3844973,
            0.6524574,
            0.5299485,
            0.6587085,
            0.5077193,
            0.5172699,
            0.5526334,
            0.5063047,
            0.6422554,
            0.7690184,
            0.8245472,
            1.261225
        ]
    },
    "n": 20,
    "expec": [
        {
            "E[P_z(1)]": 0.0008776712,
            "E[P_z(2)]": 0.0002482161,
            "E[P_z(3)]": 0.0001615971,
            "E[P_z(4)]": 0.0001221053,
            "E[P_z(5)]": 8.12761e-05,
            "E[P_z(6)]": 7.52465e-05,
            "E[P_z(7)]": 7.65909e-05,
            "E[P_z(8)]": 4.21829e-05,
            "E[P_z(9)]": 6.36272e-05,
            "E[P_z(10)]": 4.65122e-05,
            "E[P_z(11)]": 5.25575e-05,
            "E[P_z(12)]": 3.71344e-05,
            "E[P_z(13)]": 3.49229e-05,
            "E[P_z(14)]": 3.46454e-05,
            "E[P_z(15)]": 2.9625e-05,
            "E[P_z(16)]": 3.52311e-05,
            "E[P_z(17)]": 3.97034e-05,
            "E[P_z(18)]": 4.02056e-05,
            "E[P_z(19)]": 5.8264e-05,
            "E[D_z]": null,
            "E[mis_z]": null
        },
        {
            "E[P_z(1)]": 0.000597068,
            "E[P_z(2)]": 0.0001549824,
            "E[P_z(3)]": 9.67826e-05,
            "E[P_z(4)]": 7.11893e-05,
            "E[P_z(5)]": 4.64596e-05,
            "E[P_z(6)]": 4.23503e-05,
            "E[P_z(7)]": 4.25596e-05,
            "E[P_z(8)]": 2.31869e-05,
            "E[P_z(9)]": 3.46461e-05,
            "E[P_z(10)]": 2.5116e-05,
            "E[P_z(11)]": 2.8169e-05,
            "E[P_z(12)]": 1.97684e-05,
            "E[P_z(13)]": 1.84762e-05,
            "E[P_z(14)]": 1.82251e-05,
            "E[P_z(15)]": 1.55018e-05,
            "E[P_z(16)]": 1.83445e-05,
            "E[P_z(17)]": 2.05776e-05,
            "E[P_z(18)]": 2.07474e-05,
            "E[P_z(19)]": 2.99431e-05,
            "E[D_z]": null,
            "E[mis_z]": null
        }
    ],
    "alpha": 0.009076923280089673,
    "execution_time": 669.2877020835876
}