{
    "py/object": "fastdfe.polydfe.PolyDFE",
    "logger": {
        "py/reduce": [
            {
                "py/function": "logging.getLogger"
            },
            {
                "py/tuple": [
                    "fastdfe.PolyDFE"
                ]
            }
        ]
    },
    "bootstraps": null,
    "config": {
        "py/object": "fastdfe.config.Config",
        "data": {
            "model": "GammaExpParametrization",
            "intervals_del": {
                "py/tuple": [
                    -100000000.0,
                    -1e-05,
                    1000
                ]
            },
            "intervals_ben": {
                "py/tuple": [
                    1e-05,
                    10000.0,
                    1000
                ]
            },
            "integration_mode": "midpoint",
            "linearized": true,
            "seed": 0,
            "opts_mle": {},
            "n_runs": 10,
            "x0": {
                "all": {
                    "S_b": 0.03800569,
                    "S_d": -68.01433,
                    "a": -1,
                    "b": 0.1127644,
                    "eps": 4.49744e-06,
                    "eps_cont": 0,
                    "lambda": 0,
                    "p_b": 0.003905648,
                    "r": [
                        0.5669393,
                        0.5649833,
                        0.5475162,
                        0.4995644,
                        0.5648594,
                        0.6039999,
                        0.4662727,
                        0.5802472,
                        0.5323765,
                        0.5838853,
                        0.5587549,
                        0.5490204,
                        0.5681745,
                        0.5012596,
                        0.6027202,
                        0.6738647,
                        0.7739941,
                        1.427315
                    ],
                    "theta_bar": 0.0008503307
                }
            },
            "bounds": {},
            "scales": {},
            "fixed_params": {},
            "shared_params": [],
            "covariates": [],
            "sfs_neut": {
                "py/object": "fastdfe.spectrum.Spectra",
                "data": {
                    "all": [
                        1040274.81958835,
                        943.0,
                        253.0,
                        184.0,
                        107.0,
                        101.0,
                        87.0,
                        89.0,
                        59.0,
                        55.0,
                        51.0,
                        50.0,
                        54.0,
                        58.0,
                        35.0,
                        25.0,
                        38.0,
                        41.0,
                        39.0,
                        76.0,
                        0.0
                    ]
                }
            },
            "sfs_sel": {
                "py/object": "fastdfe.spectrum.Spectra",
                "data": {
                    "all": [
                        2842975.18041165,
                        1807.0,
                        460.0,
                        271.0,
                        225.0,
                        154.0,
                        158.0,
                        111.0,
                        83.0,
                        96.0,
                        73.0,
                        69.0,
                        71.0,
                        44.0,
                        70.0,
                        50.0,
                        39.0,
                        44.0,
                        53.0,
                        86.0,
                        0.0
                    ]
                }
            },
            "do_bootstrap": false,
            "n_bootstraps": 10,
            "parallelize": false,
            "loss_type": "likelihood"
        }
    },
    "output_file": null,
    "execution_time": 561.1946935653687,
    "summary": {
        "py/object": "fastdfe.polydfe.PolyDFEResult",
        "output_file": "results/polydfe/hgdp/inference/1/opts.n.20.config.default/bootstraps/42/all.polydfe.txt",
        "postprocessing_source": "../resources/polydfe/postprocessing/script.R",
        "data": {
            "output_file": "/scratch/40841176/tmpk0hm5fua",
            "model": "C",
            "likelihood": -136.1135,
            "criteria": 0.00015,
            "params_mle": {
                "eps": 4.49613e-06,
                "eps_cont": 0,
                "lambda": 0,
                "theta_bar": 0.000892445,
                "a": -1,
                "S_d": -56.76356,
                "b": 0.137141,
                "p_b": 0.003881988,
                "S_b": 0.03794658,
                "r": [
                    0.5584814,
                    0.555138,
                    0.5533802,
                    0.5407674,
                    0.6321342,
                    0.6088552,
                    0.4987657,
                    0.6015928,
                    0.552898,
                    0.5874364,
                    0.6770754,
                    0.6017095,
                    0.6703044,
                    0.5153021,
                    0.5666753,
                    0.6672381,
                    0.7674591,
                    1.43134
                ]
            },
            "n": 20,
            "expec": [
                {
                    "E[P_z(1)]": 0.0008924413,
                    "E[P_z(2)]": 0.000249206,
                    "E[P_z(3)]": 0.0001651428,
                    "E[P_z(4)]": 0.0001234649,
                    "E[P_z(5)]": 9.65207e-05,
                    "E[P_z(6)]": 9.40239e-05,
                    "E[P_z(7)]": 7.76241e-05,
                    "E[P_z(8)]": 5.56401e-05,
                    "E[P_z(9)]": 5.96542e-05,
                    "E[P_z(10)]": 4.93431e-05,
                    "E[P_z(11)]": 4.76596e-05,
                    "E[P_z(12)]": 5.03544e-05,
                    "E[P_z(13)]": 4.13073e-05,
                    "E[P_z(14)]": 4.27295e-05,
                    "E[P_z(15)]": 3.06589e-05,
                    "E[P_z(16)]": 3.16083e-05,
                    "E[P_z(17)]": 3.50284e-05,
                    "E[P_z(18)]": 3.80518e-05,
                    "E[P_z(19)]": 6.72349e-05,
                    "E[D_z]": null,
                    "E[mis_z]": null
                },
                {
                    "E[P_z(1)]": 0.0006391101,
                    "E[P_z(2)]": 0.0001591786,
                    "E[P_z(3)]": 9.93407e-05,
                    "E[P_z(4)]": 7.1401e-05,
                    "E[P_z(5)]": 5.42218e-05,
                    "E[P_z(6)]": 5.16238e-05,
                    "E[P_z(7)]": 4.18231e-05,
                    "E[P_z(8)]": 2.95017e-05,
                    "E[P_z(9)]": 3.11927e-05,
                    "E[P_z(10)]": 2.54851e-05,
                    "E[P_z(11)]": 2.43454e-05,
                    "E[P_z(12)]": 2.5466e-05,
                    "E[P_z(13)]": 2.07004e-05,
                    "E[P_z(14)]": 2.12334e-05,
                    "E[P_z(15)]": 1.51165e-05,
                    "E[P_z(16)]": 1.54715e-05,
                    "E[P_z(17)]": 1.70288e-05,
                    "E[P_z(18)]": 1.83802e-05,
                    "E[P_z(19)]": 3.22805e-05,
                    "E[D_z]": null,
                    "E[mis_z]": null
                }
            ],
            "alpha": 0.009433963961572584,
            "execution_time": 561.1946935653687
        }
    }
}