{
    "output_file": "/scratch/40841186/tmpo82mec57",
    "model": "C",
    "likelihood": -137.2611,
    "criteria": 0.00117,
    "params_mle": {
        "eps": 4.51295e-06,
        "eps_cont": 0,
        "lambda": 0,
        "theta_bar": 0.0009083384,
        "a": -1,
        "S_d": -15796.8,
        "b": 0.03949508,
        "p_b": 0.004006883,
        "S_b": 0.03863273,
        "r": [
            0.5185,
            0.5018548,
            0.470681,
            0.4331453,
            0.4483446,
            0.5115068,
            0.3671637,
            0.4733584,
            0.468929,
            0.4741685,
            0.4668748,
            0.4711712,
            0.5027454,
            0.3575983,
            0.5323429,
            0.5330187,
            0.6991708,
            1.022295
        ]
    },
    "n": 20,
    "expec": [
        {
            "E[P_z(1)]": 0.0009083345,
            "E[P_z(2)]": 0.0002354858,
            "E[P_z(3)]": 0.0001519508,
            "E[P_z(4)]": 0.0001068841,
            "E[P_z(5)]": 7.86882e-05,
            "E[P_z(6)]": 6.78746e-05,
            "E[P_z(7)]": 6.63743e-05,
            "E[P_z(8)]": 4.16886e-05,
            "E[P_z(9)]": 4.77744e-05,
            "E[P_z(10)]": 4.25946e-05,
            "E[P_z(11)]": 3.91551e-05,
            "E[P_z(12)]": 3.53401e-05,
            "E[P_z(13)]": 3.29219e-05,
            "E[P_z(14)]": 3.26189e-05,
            "E[P_z(15)]": 2.16549e-05,
            "E[P_z(16)]": 3.02221e-05,
            "E[P_z(17)]": 2.84806e-05,
            "E[P_z(18)]": 3.52833e-05,
            "E[P_z(19)]": 4.8877e-05,
            "E[D_z]": null,
            "E[mis_z]": null
        },
        {
            "E[P_z(1)]": 0.0006332689,
            "E[P_z(2)]": 0.0001582258,
            "E[P_z(3)]": 0.0001003046,
            "E[P_z(4)]": 6.97516e-05,
            "E[P_z(5)]": 5.09208e-05,
            "E[P_z(6)]": 4.36326e-05,
            "E[P_z(7)]": 4.24354e-05,
            "E[P_z(8)]": 2.65293e-05,
            "E[P_z(9)]": 3.02794e-05,
            "E[P_z(10)]": 2.68996e-05,
            "E[P_z(11)]": 2.46482e-05,
            "E[P_z(12)]": 2.2182e-05,
            "E[P_z(13)]": 2.06092e-05,
            "E[P_z(14)]": 2.03694e-05,
            "E[P_z(15)]": 1.3492e-05,
            "E[P_z(16)]": 1.87897e-05,
            "E[P_z(17)]": 1.76718e-05,
            "E[P_z(18)]": 2.18517e-05,
            "E[P_z(19)]": 3.02172e-05,
            "E[D_z]": null,
            "E[mis_z]": null
        }
    ],
    "alpha": 0.009697544673063784,
    "execution_time": 1247.6884422302246
}